Pymars_india/__init__.py
Pymars_india/__main__.py
Pymars_india-1.0.3.dist-info/LICENSE
Pymars_india-1.0.3.dist-info/METADATA
Pymars_india-1.0.3.dist-info/WHEEL
Pymars_india-1.0.3.dist-info/entry_points.txt
Pymars_india-1.0.3.dist-info/top_level.txt
Pymars_india-1.0.3.dist-info/RECORD
