Metadata-Version: 2.1
Name: Pymars-india
Version: 1.0.3
Summary: Mars orbital mission
Home-page: https://github.com/Priteshraj10/Pymars_india
Author: Pritesh Raj
Author-email: priteshraj41@gmail.com
License: MIT
Platform: UNKNOWN
Classifier: License :: OSI Approved :: MIT License
Classifier: Programming Language :: Python :: 3.6
Classifier: Programming Language :: Python :: 3.7
Classifier: Programming Language :: Python :: 3.8
Classifier: Programming Language :: Python :: 3.9
